conversation_analytics_toolkit/__init__.py
conversation_analytics_toolkit/__meta__.py
conversation_analytics_toolkit/analysis.py
conversation_analytics_toolkit/ba_transformation.py
conversation_analytics_toolkit/export.py
conversation_analytics_toolkit/filtering.py
conversation_analytics_toolkit/filtering2.py
conversation_analytics_toolkit/flowchart.min.css
conversation_analytics_toolkit/flowchart2.min.js
conversation_analytics_toolkit/flows.py
conversation_analytics_toolkit/jupyter_utils.py
conversation_analytics_toolkit/keyword_analysis.py
conversation_analytics_toolkit/selection.py
conversation_analytics_toolkit/sentiment_analysis.py
conversation_analytics_toolkit/svg_export.min.js
conversation_analytics_toolkit/transcript.min.css
conversation_analytics_toolkit/transcript.min.js
conversation_analytics_toolkit/transcript.py
conversation_analytics_toolkit/transformation.py
conversation_analytics_toolkit/visualization.py
conversation_analytics_toolkit/wa_adaptor.py
conversation_analytics_toolkit/wa_assistant_skills.py
conversation_analytics_toolkit/wa_dialog_chart.min.css
conversation_analytics_toolkit/wa_dialog_chart.min.js
conversation_analytics_toolkit/wa_model.min.js
conversation_analytics_toolkit/wa_node_details.min.js
conversation_analytics_toolkit/wa_tree.min.js
conversation_analytics_toolkit/wordpackchart.min.css
conversation_analytics_toolkit/wordpackchart.min.js
conversation_analytics_toolkit-1.9.1.dist-info/LICENSE
conversation_analytics_toolkit-1.9.1.dist-info/METADATA
conversation_analytics_toolkit-1.9.1.dist-info/WHEEL
conversation_analytics_toolkit-1.9.1.dist-info/top_level.txt
conversation_analytics_toolkit-1.9.1.dist-info/RECORD
