Metadata-Version: 2.1
Name: conversation-analytics-toolkit
Version: 1.9.1
Summary: Dialog Flow Analysis Tool for Watson Assistant
Home-page: https://github.com/watson-developer-cloud/assistant-dialog-flow-analysis
Author: IBM Watson
Author-email: watdevex@us.ibm.com
Maintainer: Avi Yaeli
Maintainer-email: aviy@il.ibm.com
License: Apache 2.0
Platform: any
Classifier: Development Status :: 4 - Beta
Classifier: Intended Audience :: Developers
Classifier: License :: OSI Approved :: Apache Software License
Classifier: Programming Language :: Python
Classifier: Programming Language :: Python :: 3
Classifier: Programming Language :: Python :: 3.6
Classifier: Programming Language :: Python :: 3.7
Classifier: Operating System :: OS Independent
Classifier: Topic :: Software Development :: Libraries :: Python Modules
License-File: LICENSE
Requires-Dist: pandas (>=1.1.0)
Requires-Dist: nltk (>=3.4.0)
Requires-Dist: textblob (>=0.15.3)
Requires-Dist: scikit-learn (>=0.21.3)
Requires-Dist: tqdm (>=4.31.1)
Requires-Dist: ipywidgets (>=7.4.2)
Requires-Dist: ibm-watson (>=4.3.0)
Requires-Dist: plotly (>=4.5.0)
Requires-Dist: requests (>=2.18.4)
